GitlabParser/__init__.py
GitlabParser/gitlab.py
GitlabParser/logger.py
gitlabparser-0.1.0.dist-info/licenses/LICENSE
gitlabparser-0.1.0.dist-info/METADATA
gitlabparser-0.1.0.dist-info/WHEEL
gitlabparser-0.1.0.dist-info/top_level.txt
gitlabparser-0.1.0.dist-info/RECORD
