Metadata-Version: 2.4
Name: GitlabParser
Version: 0.1.0
Summary: Gitlab Parser
Author-email: Vitaly Kargin <super_set@mail.ru>
License: MIT
Project-URL: Homepage, https://github.com/superset1/Python_module_Gitlab-Parser
Classifier: Programming Language :: Python :: 3
Classifier: License :: OSI Approved :: MIT License
Classifier: Operating System :: OS Independent
Requires-Python: >=3.8
License-File: LICENSE
Dynamic: license-file
